sketchtml/__init__.py
sketchtml/lzw.py
sketchtml/signature.py
sketchtml/tree.py
sketchtml-0.0.2.dist-info/DESCRIPTION.rst
sketchtml-0.0.2.dist-info/METADATA
sketchtml-0.0.2.dist-info/RECORD
sketchtml-0.0.2.dist-info/WHEEL
sketchtml-0.0.2.dist-info/metadata.json
sketchtml-0.0.2.dist-info/top_level.txt
