Metadata-Version: 2.0
Name: sketchtml
Version: 0.0.2
Summary: Helper library to experiment with HTML fingerprinting.
Home-page: https://github.com/redapple/sketchtml
Author: Paul Tremberth
Author-email: paul.tremberth@gmail.com
License: MIT license
Keywords: sketchtml
Platform: UNKNOWN
Classifier: Development Status :: 2 - Pre-Alpha
Classifier: Intended Audience :: Developers
Classifier: License :: OSI Approved :: MIT License
Classifier: Natural Language :: English
Classifier: Programming Language :: Python :: 2
Classifier: Programming Language :: Python :: 2.7
Classifier: Programming Language :: Python :: 3
Classifier: Programming Language :: Python :: 3.3
Classifier: Programming Language :: Python :: 3.4
Classifier: Programming Language :: Python :: 3.5
Classifier: Programming Language :: Python :: 3.6
Requires-Dist: lxml
